{"is_source_file": true, "format": "JavaScript (React JSX)", "description": "This source file defines a React functional component named 'Header' which provides the top navigation bar for the sneaker shop website. It includes brand logo, navigation links, a search input, and a cart toggle button with badge displaying item count.", "external_files": ["react", "react-router-dom"], "external_methods": ["Link", "NavLink"], "published": ["Header"], "classes": [], "methods": [{"name": "Header({ cartCount = 0, onToggleCart })", "description": "React functional component rendering the website header with brand, navigation, search, and cart toggle.", "scope": "", "scopeKind": ""}], "calls": ["React", "Link", "NavLink", "onToggleCart"], "search-terms": ["Header", "React", "navigation", "cart", "search", "brand", "layout"], "state": 2, "file_id": 14, "knowledge_revision": 31, "git_revision": "", "ctags": [{"_type": "tag", "name": "Header", "path": "/home/kavia/workspace/code-generation/sneaker-shop-online-platform-179105-179114/shoes_business_frontend/src/components/layout/Header.jsx", "pattern": "/^export default function Header({ cartCount = 0, onToggleCart }) {$/", "language": "JavaScript", "kind": "function", "signature": "({ cartCount = 0, onToggleCart })"}], "hash": "be4b7880949a57347f4134ab6e84fac5", "format-version": 4, "code-base-name": "shoes_business_frontend", "filename": "shoes_business_frontend/src/components/layout/Header.jsx", "revision_history": [{"31": ""}]}